stackwalker/__init__.py
stackwalker/stackwalker.py
stackwalker-0.4.2.dist-info/METADATA
stackwalker-0.4.2.dist-info/WHEEL
stackwalker-0.4.2.dist-info/top_level.txt
stackwalker-0.4.2.dist-info/RECORD
