Metadata-Version: 2.4
Name: stackwalker
Version: 0.4.2
Author-email: Joni Töyrylä <info@jonitoyryla.eu>
License-Expression: MIT
Project-URL: Source, https://github.com/Nerdman4U/stackwalker
Classifier: Intended Audience :: Developers
Classifier: Programming Language :: Python :: 3
Classifier: Development Status :: 4 - Beta
Requires-Python: >=3.10
